logginger/__init__.py
logginger/config.py
logginger/fmts.py
logginger/formatters.py
logginger/slack/__init__.py
logginger/slack/colors.py
logginger/utils.py
logginger/uvicorn/__init__.py
logginger-0.0.5.dist-info/LICENSE
logginger-0.0.5.dist-info/METADATA
logginger-0.0.5.dist-info/WHEEL
logginger-0.0.5.dist-info/RECORD
