Metadata-Version: 2.1
Name: logginger
Version: 0.0.5
Summary: Logginger is a simple logging library that includes tools to extend the logging module.
Author: Hikmat Samadov
Author-email: hikmat@cublya.com
Requires-Python: >=3.10,<4.0
Classifier: Programming Language :: Python :: 3
Classifier: Programming Language :: Python :: 3.10
Classifier: Programming Language :: Python :: 3.11
Classifier: Programming Language :: Python :: 3.12
Requires-Dist: click (>=8.1.7,<9.0.0)
Requires-Dist: six (>=1.16.0,<2.0.0)
Requires-Dist: slack-sdk (>=3.27.1,<4.0.0)
